canisius_cyb600_example/__init__.py
canisius_cyb600_example/main.py
csc_cyb600_gabe-1.0.6.data/scripts/say-hello-cyb600
csc_cyb600_jmdv/__init__.py
csc_cyb600_jmdv/main.py
csc_cyb600_gabe-1.0.6.dist-info/LICENSE
csc_cyb600_gabe-1.0.6.dist-info/METADATA
csc_cyb600_gabe-1.0.6.dist-info/WHEEL
csc_cyb600_gabe-1.0.6.dist-info/top_level.txt
csc_cyb600_gabe-1.0.6.dist-info/RECORD
